{
  "id": "HardStylishMelonHeyGuys-OxvkTYre59Xps8mZ",
  "url": "https://clips.twitch.tv/HardStylishMelonHeyGuys-OxvkTYre59Xps8mZ",
  "embed_url": "https://clips.twitch.tv/embed?clip=HardStylishMelonHeyGuys-OxvkTYre59Xps8mZ",
  "broadcaster_id": "75974647",
  "broadcaster_name": "TwitchTriesToPlay",
  "creator_id": "190192888",
  "creator_name": "FinalKuja",
  "video_id": "",
  "game_id": "2692",
  "language": "en",
  "title": "SL Reds",
  "view_count": 6,
  "created_at": "2022-01-06T14:49:13Z",
  "thumbnail_url": "https://static-cdn.jtvnw.net/twitch-clips/AT-cm%7CGH6jqTsb5E2K3ufV6bPJmQ-preview-480x272.jpg",
  "duration": 19,
  "vod_offset": null,
  "is_featured": false,
  "user_id": "75974647",
  "channel_id": "75974647",
  "created_at_for_paths": "2022_01_06T14_49_13Z",
  "created_at_millis": 1641480553000,
  "created_at_year": 2022,
  "created_at_month": 1,
  "created_at_date": 6,
  "created_at_hour": 14,
  "created_at_minute": 49,
  "created_at_second": 13,
  "created_at_millisecond": 0
}