{
  "id": "2249737303",
  "stream_id": null,
  "user_id": "75974647",
  "user_login": "twitchtriestoplay",
  "user_name": "TwitchTriesToPlay",
  "title": "Twitch Plays Kingdom Hearts 2 Re-Revisit on an actual PS2 day 25 hour 00 to hour 12 - Beating Heartless (Hollow Bastion)",
  "description": "",
  "created_at": "2024-09-13T03:29:42Z",
  "published_at": "2024-09-13T03:29:42Z",
  "url": "https://www.twitch.tv/videos/2249737303",
  "thumbnail_url": "https://static-cdn.jtvnw.net/cf_vods/d2nvs31859zcd8/a34fb678d469d11de3b6_twitchtriestoplay_44753546509_5985774703//thumb/thumb2249737303-%{width}x%{height}.jpg",
  "viewable": "public",
  "view_count": 1,
  "language": "en",
  "type": "highlight",
  "duration": "22m40s",
  "muted_segments": null,
  "created_at_for_paths": "2024_09_13T03_29_42Z",
  "created_at_millis": 1726198182000,
  "created_at_year": 2024,
  "created_at_month": 9,
  "created_at_date": 13,
  "created_at_hour": 3,
  "created_at_minute": 29,
  "created_at_second": 42,
  "created_at_millisecond": 0,
  "published_at_for_paths": "2024_09_13T03_29_42Z",
  "published_at_millis": 1726198182000,
  "published_at_year": 2024,
  "published_at_month": 9,
  "published_at_date": 13,
  "published_at_hour": 3,
  "published_at_minute": 29,
  "published_at_second": 42,
  "published_at_millisecond": 0
}