{
  "id": "735729046",
  "stream_id": null,
  "user_id": "39127626",
  "user_login": "whataboutgaminglive",
  "user_name": "WhatAboutGamingLive",
  "title": "Car game | !subtember",
  "description": "",
  "created_at": "2020-09-09T03:33:17Z",
  "published_at": "2020-09-09T03:33:17Z",
  "url": "https://www.twitch.tv/videos/735729046",
  "thumbnail_url": "https://static-cdn.jtvnw.net/cf_vods/d2nvs31859zcd8/b0930ea96126b01dc9eb_whataboutgaminglive_53590350671_9750838569//thumb/thumb735729046-%{width}x%{height}.jpg",
  "viewable": "public",
  "view_count": 2,
  "language": "en",
  "type": "highlight",
  "duration": "1h24m25s",
  "muted_segments": null,
  "created_at_for_paths": "2020_09_09T03_33_17Z",
  "created_at_millis": 1599622397000,
  "created_at_year": 2020,
  "created_at_month": 9,
  "created_at_date": 9,
  "created_at_hour": 3,
  "created_at_minute": 33,
  "created_at_second": 17,
  "created_at_millisecond": 0,
  "published_at_for_paths": "2020_09_09T03_33_17Z",
  "published_at_millis": 1599622397000,
  "published_at_year": 2020,
  "published_at_month": 9,
  "published_at_date": 9,
  "published_at_hour": 3,
  "published_at_minute": 33,
  "published_at_second": 17,
  "published_at_millisecond": 0
}