{
  "id": "WildSpunkyNoodlePastaThat-ftYHEy2OzcGpDmrJ",
  "url": "https://clips.twitch.tv/WildSpunkyNoodlePastaThat-ftYHEy2OzcGpDmrJ",
  "embed_url": "https://clips.twitch.tv/embed?clip=WildSpunkyNoodlePastaThat-ftYHEy2OzcGpDmrJ",
  "broadcaster_id": "75974647",
  "broadcaster_name": "TwitchTriesToPlay",
  "creator_id": "222830059",
  "creator_name": "greensuigi",
  "video_id": "",
  "game_id": "2692",
  "language": "en",
  "title": "lmao",
  "view_count": 145,
  "created_at": "2021-05-13T21:50:27Z",
  "thumbnail_url": "https://static-cdn.jtvnw.net/twitch-clips/41823268589-offset-165010-preview-480x272.jpg",
  "duration": 28,
  "vod_offset": null,
  "is_featured": false,
  "user_id": "75974647",
  "channel_id": "75974647",
  "created_at_for_paths": "2021_05_13T21_50_27Z",
  "created_at_millis": 1620942627000,
  "created_at_year": 2021,
  "created_at_month": 5,
  "created_at_date": 13,
  "created_at_hour": 21,
  "created_at_minute": 50,
  "created_at_second": 27,
  "created_at_millisecond": 0
}