{
  "id": "ExcitedAnnoyingBearPartyTime-__43ygRn_utHdSoI",
  "url": "https://clips.twitch.tv/ExcitedAnnoyingBearPartyTime-__43ygRn_utHdSoI",
  "embed_url": "https://clips.twitch.tv/embed?clip=ExcitedAnnoyingBearPartyTime-__43ygRn_utHdSoI",
  "broadcaster_id": "75974647",
  "broadcaster_name": "TwitchTriesToPlay",
  "creator_id": "39127626",
  "creator_name": "WhatAboutGamingLive",
  "video_id": "",
  "game_id": "2692",
  "language": "en",
  "title": "Collision???",
  "view_count": 5,
  "created_at": "2021-04-10T13:17:35Z",
  "thumbnail_url": "https://static-cdn.jtvnw.net/twitch-clips/41373847853-offset-4874-preview-480x272.jpg",
  "duration": 28,
  "vod_offset": null,
  "is_featured": false,
  "user_id": "75974647",
  "channel_id": "75974647",
  "created_at_for_paths": "2021_04_10T13_17_35Z",
  "created_at_millis": 1618060655000,
  "created_at_year": 2021,
  "created_at_month": 4,
  "created_at_date": 10,
  "created_at_hour": 13,
  "created_at_minute": 17,
  "created_at_second": 35,
  "created_at_millisecond": 0
}